<?xml version='1.0' encoding='utf8'?>
<annotation><folder>wgisd</folder><filename>CSV_1876.jpg</filename><path>/home/sgunal/Proyectos/thesis/datasets/wgisd/JPEGImages/CSV_1876.jpg</path><source><database>Unknown</database></source><size><width>2048</width><height>1365</height><depth>3</depth></size><segmented>0</segmented><object><name>uva</name><pose>Unspecified</pose><truncated>0</truncated><difficult>0</difficult><bndbox><xmin>878.618624</xmin><ymin>926.5886175000002</ymin><xmax>1064.691712</xmax><ymax>1317.2093025000001</ymax></bndbox></object><object><name>uva</name><pose>Unspecified</pose><truncated>0</truncated><difficult>0</difficult><bndbox><xmin>801.184768</xmin><ymin>514.6398075000001</ymin><xmax>1038.222336</xmax><ymax>878.4027525</ymax></bndbox></object><object><name>uva</name><pose>Unspecified</pose><truncated>0</truncated><difficult>0</difficult><bndbox><xmin>202.667008</xmin><ymin>765.8380275000001</ymin><xmax>456.690688</xmax><ymax>1183.3164525</ymax></bndbox></object><object><name>uva</name><pose>Unspecified</pose><truncated>0</truncated><difficult>0</difficult><bndbox><xmin>436.93875199999997</xmin><ymin>888.2771625000003</ymin><xmax>762.8656639999999</xmax><ymax>1242.5615475000002</ymax></bndbox></object><object><name>uva</name><pose>Unspecified</pose><truncated>0</truncated><difficult>0</difficult><bndbox><xmin>1406.418944</xmin><ymin>339.670695</ymin><xmax>1617.77664</xmax><ymax>895.386765</ymax></bndbox></object><object><name>uva</name><pose>Unspecified</pose><truncated>0</truncated><difficult>0</difficult><bndbox><xmin>1084.839936</xmin><ymin>0.39516749999999945</ymin><xmax>1368.098816</xmax><ymax>169.04501249999998</ymax></bndbox></object><object><name>uva</name><pose>Unspecified</pose><truncated>0</truncated><difficult>0</difficult><bndbox><xmin>1186.37056</xmin><ymin>360.9981375</ymin><xmax>1385.0859520000001</xmax><ymax>700.6688325</ymax></bndbox></object><object><name>uva</name><pose>Unspecified</pose><truncated>0</truncated><difficult>0</difficult><bndbox><xmin>1157.926912</xmin><ymin>142.1872725</ymin><xmax>1349.926912</xmax><ymax>314.3915775</ymax></bndbox></object><object><name>uva</name><pose>Unspecified</pose><truncated>0</truncated><difficult>0</difficult><bndbox><xmin>1658.86464</xmin><ymin>186.02834250000006</ymin><xmax>1833.8764800000001</xmax><ymax>685.2648075</ymax></bndbox></object><object><name>uva</name><pose>Unspecified</pose><truncated>0</truncated><difficult>0</difficult><bndbox><xmin>1696.7895039999999</xmin><ymin>400.495095</ymin><xmax>1876.1471999999999</xmax><ymax>805.334985</ymax></bndbox></object><object><name>uva</name><pose>Unspecified</pose><truncated>0</truncated><difficult>0</difficult><bndbox><xmin>1897.481216</xmin><ymin>334.14108000000004</ymin><xmax>2047.998976</xmax><ymax>753.59466</ymax></bndbox></object></annotation>