<?xml version='1.0' encoding='utf8'?>
<annotation><folder>wgisd</folder><filename>CSV_1873.jpg</filename><path>/home/sgunal/Proyectos/thesis/datasets/wgisd/JPEGImages/CSV_1873.jpg</path><source><database>Unknown</database></source><size><width>2048</width><height>1365</height><depth>3</depth></size><segmented>0</segmented><object><name>uva</name><pose>Unspecified</pose><truncated>0</truncated><difficult>0</difficult><bndbox><xmin>1572.864</xmin><ymin>426.0165</ymin><xmax>1703.9360000000001</xmax><ymax>527.0264999999999</ymax></bndbox></object><object><name>uva</name><pose>Unspecified</pose><truncated>0</truncated><difficult>0</difficult><bndbox><xmin>0.10240000000000293</xmin><ymin>567.9082500000001</ymin><xmax>74.0352</xmax><ymax>670.96575</ymax></bndbox></object><object><name>uva</name><pose>Unspecified</pose><truncated>0</truncated><difficult>0</difficult><bndbox><xmin>1474.9696</xmin><ymin>773.9549999999999</ymin><xmax>1671.9872</xmax><ymax>1147.965</ymax></bndbox></object><object><name>uva</name><pose>Unspecified</pose><truncated>0</truncated><difficult>0</difficult><bndbox><xmin>1357.1072</xmin><ymin>558.9675</ymin><xmax>1587.0976</xmax><ymax>982.9365</ymax></bndbox></object><object><name>uva</name><pose>Unspecified</pose><truncated>0</truncated><difficult>0</difficult><bndbox><xmin>1575.0144</xmin><ymin>670.9657500000001</ymin><xmax>1877.0944</xmax><ymax>869.0272500000001</ymax></bndbox></object><object><name>uva</name><pose>Unspecified</pose><truncated>0</truncated><difficult>0</difficult><bndbox><xmin>735.0272</xmin><ymin>332.03625</ymin><xmax>909.1071999999999</xmax><ymax>627.01275</ymax></bndbox></object><object><name>uva</name><pose>Unspecified</pose><truncated>0</truncated><difficult>0</difficult><bndbox><xmin>455.98720000000003</xmin><ymin>210.96074999999996</ymin><xmax>728.9856</xmax><ymax>814.97325</ymax></bndbox></object><object><name>uva</name><pose>Unspecified</pose><truncated>0</truncated><difficult>0</difficult><bndbox><xmin>81.92000000000002</xmin><ymin>133.01924999999997</ymin><xmax>489.8816</xmax><ymax>476.04375000000005</ymax></bndbox></object><object><name>uva</name><pose>Unspecified</pose><truncated>0</truncated><difficult>0</difficult><bndbox><xmin>242.99519999999998</xmin><ymin>414.07275</ymin><xmax>481.9968</xmax><ymax>584.0152499999999</ymax></bndbox></object></annotation>