<?xml version='1.0' encoding='utf8'?>
<annotation><folder>wgisd</folder><filename>SYH_2017-04-27_1338.jpg</filename><path>/home/sgunal/Proyectos/thesis/datasets/wgisd/JPEGImages/SYH_2017-04-27_1338.jpg</path><source><database>Unknown</database></source><size><width>2048</width><height>1365</height><depth>3</depth></size><segmented>0</segmented><object><name>uva</name><pose>Unspecified</pose><truncated>0</truncated><difficult>0</difficult><bndbox><xmin>1061.925888</xmin><ymin>922.6396725</ymin><xmax>1200.987136</xmax><ymax>1067.9862375</ymax></bndbox></object><object><name>uva</name><pose>Unspecified</pose><truncated>0</truncated><difficult>0</difficult><bndbox><xmin>976.5928959999999</xmin><ymin>958.97529</ymin><xmax>1079.308288</xmax><ymax>1098.00327</ymax></bndbox></object><object><name>uva</name><pose>Unspecified</pose><truncated>0</truncated><difficult>0</difficult><bndbox><xmin>725.3329919999999</xmin><ymin>927.3782699999999</ymin><xmax>911.801344</xmax><ymax>1167.5172599999999</ymax></bndbox></object><object><name>uva</name><pose>Unspecified</pose><truncated>0</truncated><difficult>0</difficult><bndbox><xmin>551.5048959999999</xmin><ymin>320.7115275</ymin><xmax>845.431808</xmax><ymax>680.9200125</ymax></bndbox></object><object><name>uva</name><pose>Unspecified</pose><truncated>0</truncated><difficult>0</difficult><bndbox><xmin>183.30931200000003</xmin><ymin>606.66606</ymin><xmax>619.4575360000001</xmax><ymax>846.8050499999999</ymax></bndbox></object><object><name>uva</name><pose>Unspecified</pose><truncated>0</truncated><difficult>0</difficult><bndbox><xmin>560.987136</xmin><ymin>661.9608450000001</ymin><xmax>854.9140480000001</xmax><ymax>1079.044785</ymax></bndbox></object><object><name>uva</name><pose>Unspecified</pose><truncated>0</truncated><difficult>0</difficult><bndbox><xmin>466.17395200000004</xmin><ymin>799.4088374999999</ymin><xmax>736.395264</xmax><ymax>1224.3920325</ymax></bndbox></object><object><name>uva</name><pose>Unspecified</pose><truncated>0</truncated><difficult>0</difficult><bndbox><xmin>156.44467199999997</xmin><ymin>372.8477025</ymin><xmax>290.7648</xmax><ymax>737.7954675000001</ymax></bndbox></object><object><name>uva</name><pose>Unspecified</pose><truncated>0</truncated><difficult>0</difficult><bndbox><xmin>86.913024</xmin><ymin>644.5830299999999</ymin><xmax>216.49408</xmax><ymax>867.3428399999999</ymax></bndbox></object><object><name>uva</name><pose>Unspecified</pose><truncated>0</truncated><difficult>0</difficult><bndbox><xmin>300.24703999999997</xmin><ymin>298.59375</ymin><xmax>491.456512</xmax><ymax>628.7845199999999</ymax></bndbox></object><object><name>uva</name><pose>Unspecified</pose><truncated>0</truncated><difficult>0</difficult><bndbox><xmin>1701.925888</xmin><ymin>260.67678</ymin><xmax>2047.998976</xmax><ymax>826.2672600000001</ymax></bndbox></object><object><name>uva</name><pose>Unspecified</pose><truncated>0</truncated><difficult>0</difficult><bndbox><xmin>1615.012864</xmin><ymin>477.11800500000004</ymin><xmax>1771.4575360000001</xmax><ymax>838.9057950000001</ymax></bndbox></object></annotation>